Metadata-Version: 2.1
Name: django-graphene-endpoint
Version: 1.1
Summary: Django addon to automatically configure graphql endpoints based on Django models.
Home-page: https://github.com/Elawphant/django_relay_endpoint
Author: Gevorg Hakobyan
Author-email: gevorg.hakobyan@elawphant.am
License: MIT
Classifier: Environment :: Web Environment
Classifier: Framework :: Django
Classifier: Intended Audience :: Developers
Classifier: License :: OSI Approved :: MIT License
Classifier: Operating System :: OS Independent
Classifier: Programming Language :: Python
Classifier: Programming Language :: Python :: 3
Classifier: Programming Language :: Python :: 3 :: Only
Classifier: Programming Language :: Python :: 3.8
Classifier: Programming Language :: Python :: 3.9
Classifier: Programming Language :: Python :: 3.10
Classifier: Programming Language :: Python :: 3.11
Classifier: Topic :: Software Development :: Libraries
Classifier: Topic :: Software Development :: Libraries :: Python Modules
Requires-Python: >=3.8
License-File: LICENSE
Requires-Dist: graphene-django >=3.1.5
Requires-Dist: graphene-file-upload >=1.3.0
Requires-Dist: django-filter >=23.3.0
